dxlirflowclient/__init__.py
dxlirflowclient/_version.py
dxlirflowclient/client.py
dxlirflowclient/_config/__init__.py
dxlirflowclient/_config/sample/__init__.py
dxlirflowclient/_config/sample/dxlclient.config
dxlirflowclient/_config/sample/logging.config
dxlirflowclient-1.1.2.dist-info/LICENSE
dxlirflowclient-1.1.2.dist-info/METADATA
dxlirflowclient-1.1.2.dist-info/WHEEL
dxlirflowclient-1.1.2.dist-info/top_level.txt
dxlirflowclient-1.1.2.dist-info/RECORD
