Metadata-Version: 2.1
Name: dxlirflowclient
Version: 1.1.2
Summary: opendxl_irflow_client
Home-page: https://github.com/Syncurity/opendxl-irflow-client
Author: JP Bourget, Syncurity
License: Apache 2.0
Keywords: security,syncurity,ir-flow,orchestration,opendxl,soar
Platform: UNKNOWN
Classifier: Programming Language :: Python
Classifier: Programming Language :: Python :: 2
Classifier: Programming Language :: Python :: 2.7
Classifier: Programming Language :: Python :: 3
Classifier: Programming Language :: Python :: 3.4
Classifier: Programming Language :: Python :: 3.5
Classifier: Programming Language :: Python :: 3.6
Requires-Python: >=2.7.9,!=3.0.*,!=3.1.*,!=3.2.*,!=3.3.*
Requires-Dist: requests (>=2.20.0)
Requires-Dist: irflow-client
Requires-Dist: dxlbootstrap (>=0.2.0)
Requires-Dist: dxlclient (>=4.1.0.184)
